sanic_dropzone/__init__.py
sanic_dropzone/utils.py
sanic_dropzone-1.0.0.dist-info/LICENSE
sanic_dropzone-1.0.0.dist-info/METADATA
sanic_dropzone-1.0.0.dist-info/WHEEL
sanic_dropzone-1.0.0.dist-info/top_level.txt
sanic_dropzone-1.0.0.dist-info/RECORD
