Metadata-Version: 2.1
Name: sanic-dropzone
Version: 1.0.0
Summary: Upload file in Sanic with Dropzone.js.
Home-page: UNKNOWN
License: MIT
Keywords: sanic extension development upload
Platform: any
Classifier: Programming Language :: Python :: 3.6
Classifier: Topic :: Internet :: WWW/HTTP :: Dynamic Content
Classifier: Topic :: Software Development :: Libraries :: Python Modules
Requires-Python: >=3.6
Requires-Dist: sanic
